{"A.J. Brown": "WR", "A.J. Green": "WR", "A.T. Perry": "WR", "AJ Dillon": "RB", "AJ McCarron": "QB", "Aaron Jones": "RB", "Aaron Rodgers": "QB", "Aaron Shampklin": "RB", "Abram Smith": "RB", "Adam Thielen": "WR", "Adam Trautman": "TE", "Adrian Peterson": "RB", "Aidan O'Connell": "QB", "Albert Okwuegbunam": "TE", "Alec Ingold": "FB", "Alec Pierce": "WR", "Alex Collins": "RB", "Alex McGough": "QB", "Alexander Hollins": "WR", "Alexander Mattison": "RB", "Alize Mack": "TE", "Allen Lazard": "WR", "Alvin Kamara": "RB", "Amari Cooper": "WR", "Amari Rodgers": "WR", "Ameer Abdullah": "RB", "Amon-Ra St. Brown": "WR", "Andrei Iosivas": "WR", "Andrew Ogletree": "TE", "Andy Dalton": "QB", "Andy Isabella": "WR", "Anthony Gordon": "QB", "Anthony McFarland": "RB", "Anthony Richardson": "QB", "Anthony Schwartz": "WR", "Antoine Green": "WR", "Antoine Winfield": "DB", "Antonio Brown": "WR", "Antonio Gibson": "RB", "Armani Rogers": "TE", "Ashton Dulin": "WR", "Austin Ekeler": "RB", "Austin Hooper": "TE", "Austin Walter": "RB", "Austin Watkins": "WR", "Avery Williams": "RB", "Bailey Zappe": "QB", "Baker Mayfield": "QB", "Ben Sims": "TE", "Ben Skowronek": "WR", "Bijan Robinson": "RB", "Blaine Gabbert": "QB", "Blake Bell": "TE", "Boston Scott": "RB", "Brandin Cooks": "WR", "Brandon Aiyuk": "WR", "Brandon Bolden": "RB", "Brandon Johnson": "WR", "Braxton Berrios": "WR", "Brayden Willis": "TE", "Breece Hall": "RB", "Brenden Knox": "RB", "Brenton Strange": "TE", "Breshad Perriman": "WR", "Brevin Jordan": "TE", "Brian Hill": "RB", "Brian Hoyer": "QB", "Brittain Brown": "RB", "Brock Purdy": "QB", "Brock Wright": "TE", "Bryan Edwards": "WR", "Bryant Koback": "RB", "Bryce Ford-Wheaton": "WR", "Bryce Love": "RB", "Bryce Young": "QB", "Brycen Hopkins": "TE", "Buddy Howell": "RB", "Byron Pringle": "WR", "C.J. Beathard": "QB", "C.J. Stroud": "QB", "C.J. Uzomah": "TE", "CJ Verdell": "RB", "Cade Johnson": "WR", "Cade Otton": "TE", "Calvin Ridley": "WR", "Cam Akers": "RB", "Cam Newton": "QB", "Cam Sims": "WR", "Cameron Latu": "TE", "Cameron Scarlett": "RB", "Carson Wentz": "QB", "Case Keenum": "QB", "Cedric Tillman": "WR", "Cedrick Wilson": "WR", "CeeDee Lamb": "WR", "Chandler Cox": "FB", "Charleston Rambo": "WR", "Charlie Jones": "WR", "Charlie Kolar": "TE", "Charlie Woerner": "TE", "Chase Allen": "TE", "Chase Brown": "RB", "Chase Claypool": "WR", "Chase Edmonds": "RB", "Cheyenne O'Grady": "TE", "Chris Carson": "RB", "Chris Conley": "WR", "Chris Evans": "RB", "Chris Godwin": "WR", "Chris Moore": "WR", "Chris Olave": "WR", "Chris Rodriguez": "RB", "Christian Kirk": "WR", "Christian McCaffrey": "RB", "Christian Watson": "WR", "Chuba Hubbard": "RB", "Clayton Tune": "QB", "Clyde Edwards-Helaire": "RB", "Cody Thompson": "WR", "Colby Parkinson": "TE", "Cole Beasley": "WR", "Cole Fotheringham": "TE", "Cole Kelley": "QB", "Cole Kmet": "TE", "Cole Turner": "TE", "Colin Kaepernick": "QB", "Collin Johnson": "WR", "Colt McCoy": "QB", "Colton Dowell": "WR", "Connor Heyward": "TE", "Cooper Kupp": "WR", "Cooper Rush": "QB", "Cordarrelle Patterson": "RB", "Corey Clement": "RB", "Corey Davis": "WR", "Cornell Powell": "WR", "Courtland Sutton": "WR", "Craig Reynolds": "RB", "Curtis Samuel": "WR", "D'Andre Swift": "RB", "D'Ernest Johnson": "RB", "D'Onta Foreman": "RB", "D.J. Montgomery": "WR", "DJ Moore": "WR", "DJ Turner": "WR", "DK Metcalf": "WR", "Dak Prescott": "QB", "Dallas Goedert": "TE", "Dalton Keene": "TE", "Dalton Kincaid": "TE", "Dalton Schultz": "TE", "Dalvin Cook": "RB", "Dameon Pierce": "RB", "Damien Harris": "RB", "Damien Williams": "RB", "Damiere Byrd": "WR", "Dan Arnold": "TE", "Daniel Bellinger": "TE", "Daniel Jones": "QB", "Danny Amendola": "WR", "Danny Gray": "WR", "Dante Pettis": "WR", "Dare Ogunbowale": "RB", "Darius Slayton": "WR", "Darnell Mooney": "WR", "Darnell Washington": "TE", "Darrell Henderson": "RB", "Darren Waller": "TE", "Darrynton Evans": "RB", "Daurice Fountain": "WR", "Davante Adams": "WR", "David Bell": "WR", "David Montgomery": "RB", "David Njoku": "TE", "Davis Allen": "TE", "Davis Mills": "QB", "Dawson Knox": "TE", "De'Von Achane": "RB", "DeAndre Carter": "WR", "DeAndre Hopkins": "WR", "DeSean Jackson": "WR", "DeVante Parker": "WR", "DeVonta Smith": "WR", "DeWayne McBride": "RB", "Dee Eskridge": "WR", "DeeJay Dallas": "RB", "Deebo Samuel": "WR", "Demarcus Robinson": "WR", "Demario Douglas": "WR", "Demetric Felton": "RB", "Deneric Prince": "RB", "Denzel Mims": "WR", "Deon Jackson": "RB", "Deonte Harty": "WR", "Derek Carr": "QB", "Derius Davis": "WR", "Derrick Deese": "TE", "Derrick Henry": "RB", "Derrius Guice": "RB", "Deshaun Watson": "QB", "Desmond Ridder": "QB", "Deuce Vaughn": "RB", "Deven Thompkins": "WR", "Devin Asiasi": "TE", "Devin Duvernay": "WR", "Devin Funchess": "TE", "Devin Singletary": "RB", "Devon Allen": "WR", "Devonta Freeman": "RB", "Dexter Williams": "RB", "Dez Bryant": "WR", "Dez Fitzpatrick": "WR", "Dion Lewis": "RB", "Diontae Johnson": "WR", "Dominique Dafney": "TE", "Donovan Peoples-Jones": "WR", "Dontayvion Wicks": "WR", "Dontrell Hilliard": "RB", "Dorian Thompson-Robinson": "QB", "Drake London": "WR", "Dre Miller": "TE", "Drew Brees": "QB", "Drew Lock": "QB", "Drew Sample": "TE", "Durham Smythe": "TE", "Dwayne Haskins": "QB", "Dwayne Washington": "RB", "Dyami Brown": "WR", "Easton Stick": "QB", "Elijah Cooks": "WR", "Elijah Higgins": "TE", "Elijah Holyfield": "RB", "Elijah Mitchell": "RB", "Elijah Moore": "WR", "Emeka Emezie": "WR", "Eno Benjamin": "RB", "Equanimeous St. Brown": "WR", "Eric Gray": "RB", "Eric Saubert": "TE", "Erik Ezukanma": "WR", "Evan Engram": "TE", "Evan Hull": "RB", "Ezekiel Elliott": "RB", "Feleipe Franks": "TE", "Foster Moreau": "TE", "Frank Darby": "WR", "Freddie Swain": "WR", "Gabe Davis": "WR", "Garrett Wilson": "WR", "Gary Brightwell": "RB", "Gary Jennings": "WR", "Geno Smith": "QB", "George Kittle": "TE", "George Pickens": "WR", "Gerald Everett": "TE", "Gerrit Prince": "TE", "Giovanni Ricci": "FB", "Godwin Igwebuike": "RB", "Grant Calcaterra": "TE", "Grant DuBose": "WR", "Grayson Gunter": "TE", "Greg Dortch": "WR", "Greg Dulcich": "TE", "Greg Olsen": "TE", "Gus Edwards": "RB", "Hakeem Butler": "TE", "Harrison Bryant": "TE", "Hassan Haskins": "RB", "Hayden Hurst": "TE", "Hendon Hooker": "QB", "Henry Ruggs": "WR", "Hunter Bryant": "TE", "Hunter Henry": "TE", "Hunter Long": "TE", "Hunter Luepke": "FB", "Hunter Renfrow": "WR", "Ian Book": "QB", "Ihmir Smith-Marsette": "WR", "Isaiah Ford": "WR", "Isaiah Hodgins": "WR", "Isaiah Likely": "TE", "Isaiah McKenzie": "WR", "Isaiah Spiller": "RB", "Isiah Pacheco": "RB", "Israel Abanikanda": "RB", "J.D. McKissic": "RB", "J.J. Taylor": "RB", "J.K. Dobbins": "RB", "Ja'Marr Chase": "WR", "JaMycal Hasty": "RB", "JaQuan Hardy": "RB", "Jack Stoll": "TE", "Jacob Copeland": "WR", "Jacoby Brissett": "QB", "Jacques Patrick": "RB", "Jahan Dotson": "WR", "Jahmyr Gibbs": "RB", "Jake Bargas": "FB", "Jake Bobo": "WR", "Jake Browning": "QB", "Jake Ferguson": "TE", "Jake Fromm": "QB", "Jake Haener": "QB", "Jakobi Meyers": "WR", "Jalen Brooks": "WR", "Jalen Guyton": "WR", "Jalen Hurd": "WR", "Jalen Hurts": "QB", "Jalen Nailor": "WR", "Jalen Reagor": "WR", "Jalen Tolbert": "WR", "Jalen Virgil": "WR", "Jalin Hyatt": "WR", "Jamaal Williams": "RB", "Jamal Agnew": "WR", "Jameis Winston": "QB", "James Conner": "RB", "James Cook": "RB", "James Mitchell": "TE", "James Robinson": "RB", "James Washington": "WR", "Jameson Williams": "WR", "Jamison Crowder": "WR", "Jared Bernhardt": "WR", "Jared Cook": "TE", "Jared Goff": "QB", "Jared Pinkney": "TE", "Jaren Hall": "QB", "Jaret Patterson": "RB", "Jarrett Stidham": "QB", "Jarvis Landry": "WR", "Jashaun Corbin": "RB", "Jauan Jennings": "WR", "Javonte Williams": "RB", "Jaxon Smith-Njigba": "WR", "Jayden Reed": "WR", "Jaydon Mickens": "WR", "Jaylen Waddle": "WR", "Jaylen Warren": "RB", "Jaylon Moore": "WR", "Jeff Driskel": "QB", "Jelani Woods": "TE", "Jeremiah Haydel": "WR", "Jeremy Ruckert": "TE", "Jerick McKinnon": "RB", "Jerome Ford": "RB", "Jerry Jeudy": "WR", "Jester Weah": "WR", "Jimmy Garoppolo": "QB", "Jimmy Graham": "TE", "Jody Fortson": "TE", "Joe Burrow": "QB", "Joe Flacco": "QB", "Joe Mixon": "RB", "John Bates": "TE", "John Hightower": "WR", "John Kelly": "RB", "John Ross": "WR", "Jonathan Mingo": "WR", "Jonathan Taylor": "RB", "Jonathan Ward": "RB", "Jonnu Smith": "TE", "Jordan Addison": "WR", "Jordan Akins": "TE", "Jordan Love": "QB", "Jordan Mason": "RB", "Jordan Wilkins": "RB", "Joseph Ngata": "WR", "Josh Adams": "RB", "Josh Ali": "WR", "Josh Allen": "QB", "Josh Doctson": "WR", "Josh Downs": "WR", "Josh Jacobs": "RB", "Josh Love": "QB", "Josh Oliver": "TE", "Josh Reynolds": "WR", "Josh Whyle": "TE", "Joshua Dobbs": "QB", "Joshua Kelley": "RB", "Joshua Palmer": "WR", "Josiah Deguara": "TE", "JuJu Smith-Schuster": "WR", "Julio Jones": "WR", "Julius Chestnut": "RB", "Justice Hill": "RB", "Justin Fields": "QB", "Justin Hardy": "WR", "Justin Herbert": "QB", "Justin Jackson": "RB", "Justin Jefferson": "WR", "Justin Shorter": "WR", "Justin Watson": "WR", "Justyn Ross": "WR", "Juwan Green": "WR", "Juwan Johnson": "TE", "K.J. Costello": "QB", "K.J. Osborn": "WR", "KJ Hamler": "WR", "KaVontae Turpin": "WR", "Kadarius Toney": "WR", "Kahale Warring": "TE", "Kalif Raymond": "WR", "Kameron Brown": "WR", "Kareem Hunt": "RB", "Kayshon Boutte": "WR", "Ke'Shawn Vaughn": "RB", "Keaontay Ingram": "RB", "Kearis Jackson": "WR", "Keaton Mitchell": "RB", "Keelan Cole": "WR", "Keenan Allen": "WR", "Keith Kirkwood": "WR", "Keith Smith": "FB", "Keke Coutee": "WR", "Kendall Hinton": "WR", "Kendre Miller": "RB", "Kendrick Bourne": "WR", "Kene Nwangwu": "RB", "Kenjon Barner": "RB", "Kenneth Gainwell": "RB", "Kenny Golladay": "WR", "Kenny McIntosh": "RB", "Kenny Pickett": "QB", "Kenyan Drake": "RB", "Kevin Harris": "RB", "Keytaon Thompson": "WR", "KhaDarel Hodge": "WR", "Khalil Herbert": "RB", "Khalil Shakir": "WR", "Kirk Cousins": "QB", "Kirk Merritt": "WR", "Kyle Allen": "QB", "Kyle Juszczyk": "FB", "Kyle Philips": "WR", "Kyle Pitts": "TE", "Kyle Rudolph": "TE", "Kyle Trask": "QB", "Kylen Granson": "TE", "Kyler Murray": "QB", "Kyren Williams": "RB", "La'Mical Perine": "RB", "Lamar Jackson": "QB", "Lance McCutcheon": "WR", "Laquon Treadwell": "WR", "Larry Fitzgerald": "WR", "Latavius Murray": "RB", "Lawrence Cager": "TE", "Le'Veon Bell": "RB", "LeSean McCoy": "RB", "Leonard Fournette": "RB", "Lew Nichols": "RB", "Lil'Jordan Humphrey": "WR", "Logan Thomas": "TE", "Logan Woodside": "QB", "Luke Farrell": "TE", "Luke Musgrave": "TE", "Luke Schoonmaker": "TE", "Mac Jones": "QB", "Mack Hollins": "WR", "Makai Polk": "WR", "Malik Cunningham": "QB", "Malik Davis": "RB", "Malik Taylor": "WR", "Malik Willis": "QB", "Marcus Baugh": "TE", "Marcus Mariota": "QB", "Mark Andrews": "TE", "Mark Ingram": "RB", "Marlon Mack": "RB", "Marquez Callaway": "WR", "Marquez Valdes-Scantling": "WR", "Marquise Brown": "WR", "Marquise Goodwin": "WR", "Master Teague": "RB", "Matt Barkley": "QB", "Matt Breida": "RB", "Matt Bushman": "TE", "Matt Ryan": "QB", "Matt Sokol": "TE", "Matthew Stafford": "QB", "Max Borghi": "RB", "Max Duggan": "QB", "Michael Burton": "FB", "Michael Carter": "RB", "Michael Gallup": "WR", "Michael Mayer": "TE", "Michael Thomas": "WR", "Michael Wilson": "WR", "Mike Boone": "RB", "Mike Davis": "RB", "Mike Evans": "WR", "Mike Gesicki": "TE", "Mike Thomas": "WR", "Mike White": "QB", "Mike Williams": "WR", "Miles Sanders": "RB", "Miller Forristall": "TE", "Mitch Trubisky": "QB", "Mitchell Tinsley": "WR", "Mitchell Wilcox": "TE", "Mo Alie-Cox": "TE", "Mohamed Ibrahim": "RB", "Montrell Washington": "WR", "MyCole Pruitt": "TE", "Myles Gaskin": "RB", "Myron Mitchell": "WR", "N'Keal Harry": "WR", "Najee Harris": "RB", "Nathan Rourke": "QB", "Nelson Agholor": "WR", "Nick Bowers": "TE", "Nick Boyle": "TE", "Nick Chubb": "RB", "Nick Foles": "QB", "Nick Mullens": "QB", "Nick Muse": "TE", "Nick O'Leary": "TE", "Nick Westbrook-Ikhine": "WR", "Nico Collins": "WR", "Noah Brown": "WR", "Noah Fant": "TE", "Noah Gray": "TE", "Nyheim Hines": "RB", "O.J. Howard": "TE", "Olamide Zaccheaus": "WR", "Osirus Mitchell": "WR", "PJ Walker": "QB", "Parker Washington": "WR", "Parris Campbell": "WR", "Pat Freiermuth": "TE", "Patrick Laird": "RB", "Patrick Mahomes": "QB", "Patrick Ricard": "FB", "Patrick Taylor": "RB", "Paul Perkins": "RB", "Payne Durham": "TE", "Penny Hart": "WR", "Peyton Hendershot": "TE", "Pharaoh Brown": "TE", "Pooka Williams": "RB", "Puka Nacua": "WR", "Quentin Johnston": "WR", "Quez Watkins": "WR", "Quintin Morris": "TE", "Ra'Shaun Henry": "WR", "Racey McMath": "WR", "Rachaad White": "RB", "Raheem Blackshear": "RB", "Raheem Mostert": "RB", "Rakim Jarrett": "WR", "Randall Cobb": "WR", "Rashaad Penny": "RB", "Rashard Higgins": "WR", "Rashee Rice": "WR", "Rashid Shaheed": "WR", "Rashod Bateman": "WR", "Reggie Bonnafon": "RB", "Rex Burkhead": "RB", "Rhamondre Stevenson": "RB", "Ricky Ortiz": "FB", "Rico Dowdle": "RB", "River Cracraft": "WR", "Rob Gronkowski": "TE", "Robbie Chosen": "WR", "Robert Tonyan": "TE", "Robert Woods": "WR", "Rodney Adams": "WR", "Rodney Smith": "WR", "Romeo Doubs": "WR", "Ronald Jones": "RB", "Rondale Moore": "WR", "Ronnie Bell": "WR", "Ronnie Rivers": "RB", "Roschon Johnson": "RB", "Ross Dwelley": "TE", "Royce Freeman": "RB", "Russell Gage": "WR", "Russell Wilson": "QB", "Ryan Becker": "TE", "Ryan Tannehill": "QB", "SaRodorick Thompson": "RB", "Salvon Ahmed": "RB", "Sam Darnold": "QB", "Sam Ehlinger": "QB", "Sam Howell": "QB", "Sam LaPorta": "TE", "Samaje Perine": "RB", "Sammy Watkins": "WR", "Samori Toure": "WR", "Saquon Barkley": "RB", "Scott Miller": "WR", "Sean Clifford": "QB", "Sean Tucker": "RB", "Senorise Perry": "RB", "Shane Buechele": "QB", "Shane Zylstra": "TE", "Shi Smith": "WR", "Simi Fehoko": "WR", "Sincere McCormick": "RB", "Skylar Thompson": "QB", "Skyy Moore": "WR", "Slade Bolden": "WR", "Snoop Conner": "RB", "Sony Michel": "RB", "Spencer Brown": "RB", "Stefon Diggs": "WR", "Sterling Shepard": "WR", "Stetson Bennett": "QB", "T.J. Hockenson": "TE", "T.J. Pledger": "RB", "T.Y. Hilton": "WR", "Taiwan Jones": "RB", "Tajae Sharpe": "WR", "Tank Bigsby": "RB", "Tank Dell": "WR", "Tanner Conner": "TE", "Tanner Gentry": "WR", "Tanner Morgan": "QB", "Tarik Black": "WR", "Tay Martin": "WR", "Taylor Heinicke": "QB", "Taysom Hill": "TE", "Teagan Quitoriano": "TE", "Teddy Bridgewater": "QB", "Tee Higgins": "WR", "Terry Godwin": "WR", "Terry McLaurin": "WR", "Tevin Jones": "WR", "Tim Jones": "WR", "Tim Patrick": "WR", "Tiyon Evans": "RB", "Todd Gurley": "RB", "Tom Brady": "QB", "Tom Kennedy": "WR", "Tommy Tremble": "TE", "Tony Brown": "WR", "Tony Pollard": "RB", "Tory Carter": "FB", "Travis Homer": "RB", "Travis Kelce": "TE", "Travis Vokolek": "TE", "Trayveon Williams": "RB", "Tre Nixon": "WR", "Tre Tucker": "WR", "Tre' McKitty": "TE", "Tre'Quan Smith": "WR", "Trent Sherfield": "WR", "Trent Taylor": "WR", "Trenton Irwin": "WR", "Trestan Ebner": "RB", "Trevor Lawrence": "QB", "Trevor Siemian": "QB", "Trey Lance": "QB", "Trey McBride": "TE", "Trey Palmer": "WR", "Trey Sermon": "RB", "Treylon Burks": "WR", "Troy Hairston": "RB", "Troymaine Pope": "RB", "Tua Tagovailoa": "QB", "Tucker Kraft": "TE", "Tutu Atwell": "WR", "Ty Chandler": "RB", "Ty Johnson": "RB", "Ty Montgomery": "RB", "Ty'Son Williams": "RB", "Tyjae Spears": "RB", "Tylan Wallace": "WR", "Tyler Allgeier": "RB", "Tyler Badie": "RB", "Tyler Boyd": "WR", "Tyler Conklin": "TE", "Tyler Goodson": "RB", "Tyler Higbee": "TE", "Tyler Huntley": "QB", "Tyler Johnson": "WR", "Tyler Kroft": "TE", "Tyler Lockett": "WR", "Tyler Scott": "WR", "Tyquan Thornton": "WR", "Tyree Jackson": "TE", "Tyreek Hill": "WR", "Tyrion Davis-Price": "RB", "Tyrod Taylor": "QB", "Tyson Bagent": "QB", "Van Jefferson": "WR", "Wan'Dale Robinson": "WR", "Warren Jackson": "WR", "Will Dissly": "TE", "Will Grier": "QB", "Will Levis": "QB", "Will Mallory": "TE", "Willie Snead": "WR", "Xavier Gipson": "WR", "Xavier Hutchinson": "WR", "Xazavian Valladay": "RB", "Zach Charbonnet": "RB", "Zach Ertz": "TE", "Zach Evans": "RB", "Zach Pascal": "WR", "Zach Wilson": "QB", "Zack Kuntz": "TE", "Zack Moss": "RB", "Zamir White": "RB", "Zander Horvath": "RB", "Zay Flowers": "WR", "Zay Jones": "WR", "Zonovan Knight": "RB", "Allen Robinson II": "WR", "Brian Robinson Jr.": "RB", "Calvin Austin III": "WR", "Chig Okonkwo": "TE", "DJ Chark Jr.": "WR", "Dee Wiggins": "", "Deuce Watts": "", "Donald Parham Jr.": "TE", "Gardner Minshew II": "QB", "Grant Gunnell": "", "Irv Smith Jr.": "TE", "Jaden Walley": "", "Jeff Wilson Jr.": "RB", "John Metchie III": "WR", "Kenneth Walker III": "RB", "Laviska Shenault Jr.": "WR", "Marvin Jones Jr.": "WR", "Marvin Mims Jr.": "WR", "Mecole Hardman Jr.": "WR", "Melvin Gordon III": "RB", "Michael Pittman Jr.": "WR", "Odell Beckham Jr.": "WR", "Pierre Strong Jr.": "RB", "Ray-Ray McCloud III": "WR", "Richie James Jr.": "WR", "TJ Tampa": "", "Taulia Tagovailoa": "", "Terrace Marshall Jr.": "WR", "Tony Jones Jr.": "RB", "Travis Etienne Jr.": "RB", "Velus Jones Jr.": "WR"}
